{
  "infinitive": "credere",
  "infinitive_pronunciation": "/'kredere/",
  "english": "to believe",
  "regular": true,
  "auxiliary": "avere",
  "tenses": {
    "presente": {
      "io": {
        "conjugation": "credo",
        "pronunciation": "/ˈkreːdo/",
        "english": "I believe",
        "example": "Credo nella giustizia.",
        "example_english": "I believe in justice."
      },
      "tu": {
        "conjugation": "credi",
        "pronunciation": "/ˈkreːdi/",
        "english": "you believe",
        "example": "Credi in te stesso?",
        "example_english": "Do you believe in yourself?"
      },
      "lui": {
        "conjugation": "crede",
        "pronunciation": "/ˈkreːde/",
        "english": "he/she/it believes",
        "example": "Crede fermamente nei suoi principi.",
        "example_english": "She firmly believes in her principles."
      },
      "noi": {
        "conjugation": "crediamo",
        "pronunciation": "/crediamo/",
        "english": "we believe",
        "example": "Noi crediamo insieme.",
        "example_english": "We believe together."
      },
      "voi": {
        "conjugation": "credete",
        "pronunciation": "/credete/",
        "english": "you believe",
        "example": "Voi credete bene?",
        "example_english": "Do you believe well?"
      },
      "loro": {
        "conjugation": "credono",
        "pronunciation": "/credono/",
        "english": "they believe",
        "example": "Loro credono spesso.",
        "example_english": "They believe often."
      }
    },
    "futuro_semplice": {
      "io": {
        "conjugation": "crederò",
        "pronunciation": "/crederò/",
        "english": "I will believe",
        "example": "Io crederò ogni giorno.",
        "example_english": "I believe every day."
      },
      "tu": {
        "conjugation": "crederai",
        "pronunciation": "/crederai/",
        "english": "you (informal) will believe",
        "example": "Tu crederai bene.",
        "example_english": "You believe well."
      },
      "lui": {
        "conjugation": "crederà",
        "pronunciation": "/crederà/",
        "english": "he/she/it will believe",
        "example": "Lei crederà molto.",
        "example_english": "She believe a lot."
      },
      "noi": {
        "conjugation": "crederemo",
        "pronunciation": "/crederemo/",
        "english": "we will believe",
        "example": "Noi crederemo insieme.",
        "example_english": "We believe together."
      },
      "voi": {
        "conjugation": "crederete",
        "pronunciation": "/crederete/",
        "english": "you (plural) will believe",
        "example": "Voi crederete bene?",
        "example_english": "Do you believe well?"
      },
      "loro": {
        "conjugation": "crederanno",
        "pronunciation": "/crederanno/",
        "english": "they will believe",
        "example": "Loro crederanno spesso.",
        "example_english": "They believe often."
      }
    },
    "passato_prossimo": {
      "io": {
        "conjugation": "ho creduto",
        "pronunciation": "/ho creduto/",
        "english": "I believed",
        "example": "Ieri ho creduto.",
        "example_english": "Yesterday i believed."
      },
      "tu": {
        "conjugation": "hai creduto",
        "pronunciation": "/hai/",
        "english": "you (informal) believed",
        "example": "Ieri hai creduto.",
        "example_english": "Yesterday you (informal) believed."
      },
      "lui": {
        "conjugation": "ha creduto",
        "pronunciation": "/ha creduto/",
        "english": "he/she/it believed",
        "example": "Ieri ha creduto.",
        "example_english": "Yesterday he/she/it believed."
      },
      "noi": {
        "conjugation": "abbiamo creduto",
        "pronunciation": "/abbiamo/",
        "english": "we believed",
        "example": "Ieri abbiamo creduto.",
        "example_english": "Yesterday we believed."
      },
      "voi": {
        "conjugation": "avete creduto",
        "pronunciation": "/avete/",
        "english": "you (plural) believed",
        "example": "Ieri avete creduto.",
        "example_english": "Yesterday you (plural) believed."
      },
      "loro": {
        "conjugation": "hanno creduto",
        "pronunciation": "/hanno/",
        "english": "they believed",
        "example": "Ieri hanno creduto.",
        "example_english": "Yesterday they believed."
      }
    }
  },
  "participio_passato": {
    "form": "creduto",
    "pronunciation": "/kreˈduːto/",
    "english": "believed",
    "example": "Una storia creduta da tutti.",
    "example_english": "A story believed by everyone."
  },
  "part_of_speech": "verb",
  "context": "To believe in something or someone; faith or opinion",
  "synonyms": "ritenere,pensare"
}